{
  "MANAGEMENT_REPORTS_DATA": [
    {
      "sandi_pjp": "777930050",
      "nama_pjp": "PT. Kredigram Pembayaran Elektronis",
      "tahun_laporan": 2020,
      "nomor_surat": "LM-KG-2020-001",
      "tanggal_surat": "2021-01-15",
      "penilaian_perkembangan_industri_sp": "Perkembangan industri SP stabil, namun perlu adaptasi teknologi baru.",
      "penilaian_perkembangan_industri_sp_status": true,
      "pengawasan_perkembangan_bisnis_pjp": "Bisnis PJP tumbuh moderat, infrastruktur IT perlu peningkatan.",
      "pengawasan_perkembangan_bisnis_pjp_status": true,
      "pengawasan_tata_kelola_pjp": "Tata kelola dasar sudah diterapkan, manajemen risiko perlu diperkuat.",
      "pengawasan_tata_kelola_pjp_status": true,
      "pandangan_perbaikan_pjp": "Fokus pada digitalisasi layanan dan peningkatan keamanan siber.",
      "pandangan_perbaikan_pjp_status": true,
      "perubahan_komposisi_komisaris": "Tidak ada perubahan komposisi Dewan Komisaris.",
      "perubahan_komposisi_komisaris_status": false,
      "implementasi_kebijakan_direksi": "Kebijakan direksi telah diimplementasikan dengan baik, namun ada beberapa penyesuaian.",
      "implementasi_kebijakan_direksi_status": true,
      "proses_pencapaian_kinerja": "Proses pencapaian kinerja berjalan sesuai rencana, dengan sedikit deviasi.",
      "proses_pencapaian_kinerja_status": true,
      "perbandingan_target_dan_realisasi": "Target pendapatan tercapai 90%, realisasi SDM 85%.",
      "perbandingan_target_dan_realisasi_status": true,
      "kendala_yang_dihadapi_pjp": "Kendala utama adalah persaingan pasar yang ketat dan regulasi yang dinamis.",
      "kendala_yang_dihadapi_pjp_status": true,
      "tata_kelola_pengawasan_direksi_komisaris": "Pengawasan direksi dan dewan komisaris cukup aktif.",
      "tata_kelola_pengawasan_direksi_komisaris_status": true,
      "tata_kelola_risiko_sdm": "Proses manajemen risiko SDM perlu perbaikan dalam identifikasi risiko.",
      "tata_kelola_risiko_sdm_status": true,
      "tata_kelola_ketersediaan_prosedur": "Prosedur operasional standar tersedia, namun perlu tinjauan berkala.",
      "tata_kelola_ketersediaan_prosedur_status": true,
      "tata_kelola_pengendalian_intern": "Sistem pengendalian intern berfungsi, namun perlu penguatan di beberapa area.",
      "tata_kelola_pengendalian_intern_status": true,
      "asesmen_kualitatif_sdm": "Rencana pengembangan SDM sudah ada, namun implementasi perlu dipercepat.",
      "asesmen_kualitatif_sdm_status": true,
      "asesmen_kuantitatif_sdm": "Kecukupan SDM memadai, 2 jabatan kosong diisi dalam Q1 2021.",
      "asesmen_kuantitatif_sdm_status": true,
      "asesmen_kepemilikan_domestik_asing": "Struktur kepemilikan sesuai PBI PJP pasal 19.",
      "asesmen_kepemilikan_domestik_asing_status": true,
      "asesmen_pengendalian_domestik_asing": "Struktur pengendalian sesuai PBI PJP pasal 20.",
      "asesmen_pengendalian_domestik_asing_status": true,
      "asesmen_pemenuhan_modal": "Permodalan memenuhi kewajiban, tidak ada rencana penambahan modal.",
      "asesmen_pemenuhan_modal_status": true,
      "asesmen_manajemen_risiko_it": "Manajemen risiko IT diterapkan, perlu audit eksternal rutin.",
      "asesmen_manajemen_risiko_it_status": true,
      "pemantauan_kepatuhan": "Pemantauan kepatuhan dilakukan secara berkala, dengan komitmen perbaikan.",
      "pemantauan_kepatuhan_status": true,
      "persentase_kepemilikan_domestik": 70,
      "pengendalian_domestik": 3,
      "persentase_kepemilikan_asing": 30,
      "pengendalian_asing": 1,
      "pihak_pengendali_ubo": "PT. Induk Kredigram",
      "keterangan": "Laporan ini mencakup evaluasi kinerja tahunan dan rekomendasi untuk tahun berikutnya.",
      "file_url": "https://example.com/laporan_manajemen/KG/2020/LM-KG-2020-001.pdf",
      "file_path": "laporan_manajemen/KG/2020/LM-KG-2020-001.pdf",
      "created_at": "2021-01-20T10:00:00+07:00",
      "manajemen_sign": [
        {
          "nama": "Dr. Andika Pratama",
          "jabatan": "Komisaris Utama",
          "klasifikasi": "Komisaris"
        },
        {
          "nama": "Siti Rahayu",
          "jabatan": "Direktur Utama",
          "klasifikasi": "Direksi"
        },
        {
          "nama": "Bambang Wijaya",
          "jabatan": "Direktur Keuangan",
          "klasifikasi": "Direksi"
        }
      ]
    },
    {
      "sandi_pjp": "777930050",
      "nama_pjp": "PT. Kredigram Pembayaran Elektronis",
      "tahun_laporan": 2021,
      "nomor_surat": "LM-KG-2021-002",
      "tanggal_surat": "2022-01-18",
      "penilaian_perkembangan_industri_sp": "Industri SP berkembang pesat, Kredigram berhasil mempertahankan pangsa pasar.",
      "penilaian_perkembangan_industri_sp_status": true,
      "pengawasan_perkembangan_bisnis_pjp": "Kinerja bisnis sangat baik, fokus pada ekspansi layanan digital.",
      "pengawasan_perkembangan_bisnis_pjp_status": true,
      "pengawasan_tata_kelola_pjp": "Tata kelola dan manajemen risiko telah diperkuat, sesuai standar.",
      "pengawasan_tata_kelola_pjp_status": true,
      "pandangan_perbaikan_pjp": "Tingkatkan inovasi produk dan perluas jangkauan ke segmen baru.",
      "pandangan_perbaikan_pjp_status": true,
      "perubahan_komposisi_komisaris": "Penambahan 1 anggota Komisaris Independen.",
      "perubahan_komposisi_komisaris_status": true,
      "implementasi_kebijakan_direksi": "Kebijakan direksi diimplementasikan secara efektif, mencapai target strategis.",
      "implementasi_kebijakan_direksi_status": true,
      "proses_pencapaian_kinerja": "Pencapaian kinerja melebihi target, efisiensi operasional meningkat.",
      "proses_pencapaian_kinerja_status": true,
      "perbandingan_target_dan_realisasi": "Target laba bersih tercapai 110%, realisasi pengembangan produk 100%.",
      "perbandingan_target_dan_realisasi_status": true,
      "kendala_yang_dihadapi_pjp": "Tantangan dalam akuisisi talenta IT yang berkualitas.",
      "kendala_yang_dihadapi_pjp_status": true,
      "tata_kelola_pengawasan_direksi_komisaris": "Pengawasan aktif dan kolaboratif antara direksi dan dewan komisaris.",
      "tata_kelola_pengawasan_direksi_komisaris_status": true,
      "tata_kelola_risiko_sdm": "Proses manajemen risiko SDM terintegrasi dengan baik.",
      "tata_kelola_risiko_sdm_status": true,
      "tata_kelola_ketersediaan_prosedur": "Seluruh kebijakan dan prosedur telah diperbarui dan tersedia.",
      "tata_kelola_ketersediaan_prosedur_status": true,
      "tata_kelola_pengendalian_intern": "Sistem pengendalian intern sangat efektif, minim temuan audit.",
      "tata_kelola_pengendalian_intern_status": true,
      "asesmen_kualitatif_sdm": "Rencana pengembangan SDM berjalan baik, karyawan menunjukkan peningkatan kompetensi.",
      "asesmen_kualitatif_sdm_status": true,
      "asesmen_kuantitatif_sdm": "Kecukupan SDM optimal, tidak ada jabatan kosong signifikan.",
      "asesmen_kuantitatif_sdm_status": true,
      "asesmen_kepemilikan_domestik_asing": "Struktur kepemilikan stabil, sesuai regulasi.",
      "asesmen_kepemilikan_domestik_asing_status": true,
      "asesmen_pengendalian_domestik_asing": "Struktur pengendalian kuat, tidak ada isu kepatuhan.",
      "asesmen_pengendalian_domestik_asing_status": true,
      "asesmen_pemenuhan_modal": "Kewajiban permodalan terpenuhi dengan surplus.",
      "asesmen_pemenuhan_modal_status": true,
      "asesmen_manajemen_risiko_it": "Manajemen risiko IT proaktif, dengan sistem deteksi dini.",
      "asesmen_manajemen_risiko_it_status": true,
      "pemantauan_kepatuhan": "Pemantauan kepatuhan sangat ketat, komitmen tinggi dari seluruh jajaran.",
      "pemantauan_kepatuhan_status": true,
      "persentase_kepemilikan_domestik": 70,
      "pengendalian_domestik": 3,
      "persentase_kepemilikan_asing": 30,
      "pengendalian_asing": 1,
      "pihak_pengendali_ubo": "PT. Induk Kredigram",
      "keterangan": "Laporan ini menyoriti keberhasilan PJP dalam mencapai target strategis.",
      "file_url": "https://example.com/laporan_manajemen/KG/2021/LM-KG-2021-002.pdf",
      "file_path": "laporan_manajemen/KG/2021/LM-KG-2021-002.pdf",
      "created_at": "2022-01-25T10:00:00+07:00",
      "manajemen_sign": [
        {
          "nama": "Dr. Andika Pratama",
          "jabatan": "Komisaris Utama",
          "klasifikasi": "Komisaris"
        },
        {
          "nama": "Prof. Lina Suryani",
          "jabatan": "Komisaris Independen",
          "klasifikasi": "Komisaris"
        },
        {
          "nama": "Siti Rahayu",
          "jabatan": "Direktur Utama",
          "klasifikasi": "Direksi"
        },
        {
          "nama": "Bambang Wijaya",
          "jabatan": "Direktur Keuangan",
          "klasifikasi": "Direksi"
        }
      ]
    },
    {
      "sandi_pjp": "777930050",
      "nama_pjp": "PT. Kredigram Pembayaran Elektronis",
      "tahun_laporan": 2022,
      "nomor_surat": "LM-KG-2022-003",
      "tanggal_surat": "2023-01-10",
      "penilaian_perkembangan_industri_sp": "Dinamika industri SP menuntut adaptasi cepat, Kredigram merespons dengan baik.",
      "penilaian_perkembangan_industri_sp_status": true,
      "pengawasan_perkembangan_bisnis_pjp": "Bisnis terus berkembang, fokus pada diversifikasi produk.",
      "pengawasan_perkembangan_bisnis_pjp_status": true,
      "pengawasan_tata_kelola_pjp": "Tata kelola dan manajemen risiko sangat matang, sesuai praktik terbaik.",
      "pengawasan_tata_kelola_pjp_status": true,
      "pandangan_perbaikan_pjp": "Perkuat ekosistem kemitraan dan tingkatkan pengalaman pengguna.",
      "pandangan_perbaikan_pjp_status": true,
      "perubahan_komposisi_komisaris": "Tidak ada perubahan signifikan.",
      "perubahan_komposisi_komisaris_status": false,
      "implementasi_kebijakan_direksi": "Implementasi kebijakan direksi berjalan mulus, mendukung pertumbuhan berkelanjutan.",
      "implementasi_kebijakan_direksi_status": true,
      "proses_pencapaian_kinerja": "Pencapaian kinerja konsisten, dengan peningkatan kualitas layanan.",
      "proses_pencapaian_kinerja_status": true,
      "perbandingan_target_dan_realisasi": "Target pertumbuhan pengguna tercapai 105%, realisasi efisiensi operasional 98%.",
      "perbandingan_target_dan_realisasi_status": true,
      "kendala_yang_dihadapi_pjp": "Fluktuasi nilai tukar mata uang asing berdampak pada transaksi internasional.",
      "kendala_yang_dihadapi_pjp_status": true,
      "tata_kelola_pengawasan_direksi_komisaris": "Pengawasan sangat efektif, mendukung pengambilan keputusan strategis.",
      "tata_kelola_pengawasan_direksi_komisaris_status": true,
      "tata_kelola_risiko_sdm": "Manajemen risiko SDM proaktif, dengan program retensi talenta.",
      "tata_kelola_risiko_sdm_status": true,
      "tata_kelola_ketersediaan_prosedur": "Seluruh prosedur telah diotomatisasi dan mudah diakses.",
      "tata_kelola_ketersediaan_prosedur_status": true,
      "tata_kelola_pengendalian_intern": "Sistem pengendalian intern terintegrasi penuh, memberikan jaminan tinggi.",
      "tata_kelola_pengendalian_intern_status": true,
      "asesmen_kualitatif_sdm": "Kualitas SDM sangat baik, program pelatihan disesuaikan dengan kebutuhan industri.",
      "asesmen_kualitatif_sdm_status": true,
      "asesmen_kuantitatif_sdm": "Kecukupan SDM optimal, rotasi karyawan rendah.",
      "asesmen_kuantitatif_sdm_status": true,
      "asesmen_kepemilikan_domestik_asing": "Tidak ada perubahan signifikan pada struktur kepemilikan.",
      "asesmen_kepemilikan_domestik_asing_status": true,
      "asesmen_pengendalian_domestik_asing": "Struktur pengendalian tetap kuat, tidak ada isu baru.",
      "asesmen_pengendalian_domestik_asing_status": true,
      "asesmen_pemenuhan_modal": "Permodalan sangat kuat, jauh di atas batas minimum.",
      "asesmen_pemenuhan_modal_status": true,
      "asesmen_manajemen_risiko_it": "Manajemen risiko IT sangat canggih, dengan investasi pada AI untuk deteksi anomali.",
      "asesmen_manajemen_risiko_it_status": true,
      "pemantauan_kepatuhan": "Pemantauan kepatuhan proaktif, dengan sistem pelaporan real-time.",
      "pemantauan_kepatuhan_status": true,
      "persentase_kepemilikan_domestik": 70,
      "pengendalian_domestik": 3,
      "persentase_kepemilikan_asing": 30,
      "pengendalian_asing": 1,
      "pihak_pengendali_ubo": "PT. Induk Kredigram",
      "keterangan": "Laporan ini menunjukkan komitmen PJP terhadap inovasi dan kepatuhan.",
      "file_url": "https://example.com/laporan_manajemen/KG/2022/LM-KG-2022-003.pdf",
      "file_path": "laporan_manajemen/KG/2022/LM-KG-2022-003.pdf",
      "created_at": "2023-01-15T10:00:00+07:00",
      "manajemen_sign": [
        {
          "nama": "Dr. Andika Pratama",
          "jabatan": "Komisaris Utama",
          "klasifikasi": "Komisaris"
        },
        {
          "nama": "Prof. Lina Suryani",
          "jabatan": "Komisaris Independen",
          "klasifikasi": "Komisaris"
        },
        {
          "nama": "Siti Rahayu",
          "jabatan": "Direktur Utama",
          "klasifikasi": "Direksi"
        },
        {
          "nama": "Bambang Wijaya",
          "jabatan": "Direktur Keuangan",
          "klasifikasi": "Direksi"
        },
        {
          "nama": "Dewi Sartika",
          "jabatan": "Direktur Operasional",
          "klasifikasi": "Direksi"
        }
      ]
    },
    {
      "sandi_pjp": "777930050",
      "nama_pjp": "PT. Kredigram Pembayaran Elektronis",
      "tahun_laporan": 2023,
      "nomor_surat": "LM-KG-2023-004",
      "tanggal_surat": "2024-01-20",
      "penilaian_perkembangan_industri_sp": "Industri SP menghadapi tantangan global, namun fundamental tetap kuat.",
      "penilaian_perkembangan_industri_sp_status": true,
      "pengawasan_perkembangan_bisnis_pjp": "Bisnis menunjukkan ketahanan, strategi mitigasi risiko berjalan baik.",
      "pengawasan_perkembangan_bisnis_pjp_status": true,
      "pengawasan_tata_kelola_pjp": "Tata kelola dan manajemen risiko terus ditingkatkan, responsif terhadap perubahan.",
      "pengawasan_tata_kelola_pjp_status": true,
      "pandangan_perbaikan_pjp": "Optimalkan penggunaan data untuk personalisasi layanan dan efisiensi.",
      "pandangan_perbaikan_pjp_status": true,
      "perubahan_komposisi_komisaris": "Tidak ada perubahan signifikan.",
      "perubahan_komposisi_komisaris_status": false,
      "implementasi_kebijakan_direksi": "Kebijakan direksi berhasil menjaga stabilitas di tengah ketidakpastian ekonomi.",
      "implementasi_kebijakan_direksi_status": true,
      "proses_pencapaian_kinerja": "Pencapaian kinerja stabil, fokus pada retensi pelanggan.",
      "proses_pencapaian_kinerja_status": true,
      "perbandingan_target_dan_realisasi": "Target pertumbuhan moderat tercapai 95%, realisasi pengurangan biaya operasional 102%.",
      "perbandingan_target_dan_realisasi_status": true,
      "kendala_yang_dihadapi_pjp": "Isu privasi data dan keamanan siber yang semakin kompleks.",
      "kendala_yang_dihadapi_pjp_status": true,
      "tata_kelola_pengawasan_direksi_komisaris": "Pengawasan proaktif, memastikan kepatuhan terhadap regulasi baru.",
      "tata_kelola_pengawasan_direksi_komisaris_status": true,
      "tata_kelola_risiko_sdm": "Manajemen risiko SDM adaptif, dengan program pelatihan keamanan data.",
      "tata_kelola_risiko_sdm_status": true,
      "tata_kelola_ketersediaan_prosedur": "Prosedur keamanan data dan privasi telah diperbarui dan diimplementasikan.",
      "tata_kelola_ketersediaan_prosedur_status": true,
      "tata_kelola_pengendalian_intern": "Sistem pengendalian intern terus diperkuat untuk menghadapi ancaman siber.",
      "tata_kelola_pengendalian_intern_status": true,
      "asesmen_kualitatif_sdm": "Kompetensi SDM di bidang keamanan siber ditingkatkan melalui sertifikasi.",
      "asesmen_kualitatif_sdm_status": true,
      "asesmen_kuantitatif_sdm": "Perekrutan ahli keamanan siber dilakukan untuk mengisi kebutuhan.",
      "asesmen_kuantitatif_sdm_status": true,
      "asesmen_kepemilikan_domestik_asing": "Struktur kepemilikan tidak berubah.",
      "asesmen_kepemilikan_domestik_asing_status": true,
      "asesmen_pengendalian_domestik_asing": "Struktur pengendalian tetap solid.",
      "asesmen_pengendalian_domestik_asing_status": true,
      "asesmen_pemenuhan_modal": "Permodalan tetap kuat, tidak ada risiko kekurangan modal.",
      "asesmen_pemenuhan_modal_status": true,
      "asesmen_manajemen_risiko_it": "Manajemen risiko IT sangat fokus pada pencegahan serangan siber.",
      "asesmen_manajemen_risiko_it_status": true,
      "pemantauan_kepatuhan": "Pemantauan kepatuhan terhadap regulasi privasi data sangat ketat.",
      "pemantauan_kepatuhan_status": true,
      "persentase_kepemilikan_domestik": 70,
      "pengendalian_domestik": 3,
      "persentase_kepemilikan_asing": 30,
      "pengendalian_asing": 1,
      "pihak_pengendali_ubo": "PT. Induk Kredigram",
      "keterangan": "Laporan ini menekankan pentingnya keamanan data dan privasi pelanggan.",
      "file_url": "https://example.com/laporan_manajemen/KG/2023/LM-KG-2023-004.pdf",
      "file_path": "laporan_manajemen/KG/2023/LM-KG-2023-004.pdf",
      "created_at": "2024-01-25T10:00:00+07:00",
      "manajemen_sign": [
        {
          "nama": "Dr. Andika Pratama",
          "jabatan": "Komisaris Utama",
          "klasifikasi": "Komisaris"
        },
        {
          "nama": "Prof. Lina Suryani",
          "jabatan": "Komisaris Independen",
          "klasifikasi": "Komisaris"
        },
        {
          "nama": "Siti Rahayu",
          "jabatan": "Direktur Utama",
          "klasifikasi": "Direksi"
        },
        {
          "nama": "Bambang Wijaya",
          "jabatan": "Direktur Keuangan",
          "klasifikasi": "Direksi"
        },
        {
          "nama": "Dewi Sartika",
          "jabatan": "Direktur Operasional",
          "klasifikasi": "Direksi"
        }
      ]
    },
    {
      "sandi_pjp": "777930050",
      "nama_pjp": "PT. Kredigram Pembayaran Elektronis",
      "tahun_laporan": 2024,
      "nomor_surat": "LM-KG-2024-005",
      "tanggal_surat": "2025-01-10",
      "penilaian_perkembangan_industri_sp": "Industri SP di ambang revolusi AI, Kredigram siap berinovasi.",
      "penilaian_perkembangan_industri_sp_status": true,
      "pengawasan_perkembangan_bisnis_pjp": "Bisnis menunjukkan pertumbuhan akseleratif, investasi pada teknologi AI.",
      "pengawasan_perkembangan_bisnis_pjp_status": true,
      "pengawasan_tata_kelola_pjp": "Tata kelola dan manajemen risiko sangat adaptif terhadap inovasi teknologi.",
      "pengawasan_tata_kelola_pjp_status": true,
      "pandangan_perbaikan_pjp": "Pimpin pasar dengan solusi pembayaran berbasis AI dan blockchain.",
      "pandangan_perbaikan_pjp_status": true,
      "perubahan_komposisi_komisaris": "Penambahan 1 anggota Komisaris (Ahli Teknologi).",
      "perubahan_komposisi_komisaris_status": true,
      "implementasi_kebijakan_direksi": "Kebijakan direksi berhasil mendorong adopsi teknologi baru dan ekspansi pasar.",
      "implementasi_kebijakan_direksi_status": true,
      "proses_pencapaian_kinerja": "Pencapaian kinerja luar biasa, dengan peningkatan signifikan dalam efisiensi dan kepuasan pelanggan.",
      "proses_pencapaian_kinerja_status": true,
      "perbandingan_target_dan_realisasi": "Target inovasi produk tercapai 120%, realisasi ekspansi pasar 115%.",
      "perbandingan_target_dan_realisasi_status": true,
      "kendala_yang_dihadapi_pjp": "Regulasi yang belum matang terkait teknologi baru seperti AI dan kripto.",
      "kendala_yang_dihadapi_pjp_status": true,
      "tata_kelola_pengawasan_direksi_komisaris": "Pengawasan sangat strategis, berfokus pada risiko dan peluang teknologi baru.",
      "tata_kelola_pengawasan_direksi_komisaris_status": true,
      "tata_kelola_risiko_sdm": "Manajemen risiko SDM mengidentifikasi kebutuhan talenta AI dan data scientist.",
      "tata_kelola_risiko_sdm_status": true,
      "tata_kelola_ketersediaan_prosedur": "Prosedur untuk pengembangan dan implementasi AI telah disusun.",
      "tata_kelola_ketersediaan_prosedur_status": true,
      "tata_kelola_pengendalian_intern": "Sistem pengendalian intern diperbarui untuk mencakup risiko AI dan data besar.",
      "tata_kelola_pengendalian_intern_status": true,
      "asesmen_kualitatif_sdm": "Program pelatihan intensif untuk SDM di bidang AI dan data science.",
      "asesmen_kualitatif_sdm_status": true,
      "asesmen_kuantitatif_sdm": "Perekrutan besar-besaran untuk talenta AI dan data scientist.",
      "asesmen_kuantitatif_sdm_status": true,
      "asesmen_kepemilikan_domestik_asing": "Struktur kepemilikan tetap stabil.",
      "asesmen_kepemilikan_domestik_asing_status": true,
      "asesmen_pengendalian_domestik_asing": "Struktur pengendalian kuat, mendukung keputusan investasi teknologi.",
      "asesmen_pengendalian_domestik_asing_status": true,
      "asesmen_pemenuhan_modal": "Permodalan sangat kuat, mendukung investasi strategis.",
      "asesmen_pemenuhan_modal_status": true,
      "asesmen_manajemen_risiko_it": "Manajemen risiko IT berfokus pada risiko AI, etika, dan keamanan data.",
      "asesmen_manajemen_risiko_it_status": true,
      "pemantauan_kepatuhan": "Pemantauan kepatuhan aktif terhadap regulasi teknologi yang berkembang.",
      "pemantauan_kepatuhan_status": true,
      "persentase_kepemilikan_domestik": 70,
      "pengendalian_domestik": 3,
      "persentase_kepemilikan_asing": 30,
      "pengendalian_asing": 1,
      "pihak_pengendali_ubo": "PT. Induk Kredigram",
      "keterangan": "Laporan ini menunjukkan visi Kredigram dalam memimpin inovasi di industri SP.",
      "file_url": "https://example.com/laporan_manajemen/KG/2024/LM-KG-2024-005.pdf",
      "file_path": "laporan_manajemen/KG/2024/LM-KG-2024-005.pdf",
      "created_at": "2025-01-15T10:00:00+07:00",
      "manajemen_sign": [
        {
          "nama": "Dr. Andika Pratama",
          "jabatan": "Komisaris Utama",
          "klasifikasi": "Komisaris"
        },
        {
          "nama": "Prof. Lina Suryani",
          "jabatan": "Komisaris Independen",
          "klasifikasi": "Komisaris"
        },
        {
          "nama": "Dr. Candra Wijaya",
          "jabatan": "Komisaris (Ahli Teknologi)",
          "klasifikasi": "Komisaris"
        },
        {
          "nama": "Siti Rahayu",
          "jabatan": "Direktur Utama",
          "klasifikasi": "Direksi"
        },
        {
          "nama": "Bambang Wijaya",
          "jabatan": "Direktur Keuangan",
          "klasifikasi": "Direksi"
        },
        {
          "nama": "Dewi Sartika",
          "jabatan": "Direktur Operasional",
          "klasifikasi": "Direksi"
        }
      ]
    },
    {
      "sandi_pjp": "777956111",
      "nama_pjp": "PT. Syaftraco (d/h CV. Syaftraco)",
      "tahun_laporan": 2022,
      "nomor_surat": "LM-SFT-2022-001",
      "tanggal_surat": "2023-02-10",
      "penilaian_perkembangan_industri_sp": "Industri SP mulai stabil, persaingan meningkat.",
      "penilaian_perkembangan_industri_sp_status": true,
      "pengawasan_perkembangan_bisnis_pjp": "Bisnis Syaftraco menunjukkan pertumbuhan positif, namun perlu inovasi.",
      "pengawasan_perkembangan_bisnis_pjp_status": true,
      "pengawasan_tata_kelola_pjp": "Tata kelola dan manajemen risiko mulai matang, dengan beberapa perbaikan.",
      "pengawasan_tata_kelola_pjp_status": true,
      "pandangan_perbaikan_pjp": "Diversifikasi layanan dan peningkatan kualitas SDM.",
      "pandangan_perbaikan_pjp_status": true,
      "perubahan_komposisi_komisaris": "Tidak ada perubahan.",
      "perubahan_komposisi_komisaris_status": false,
      "implementasi_kebijakan_direksi": "Kebijakan direksi berhasil mendorong pertumbuhan, namun efisiensi masih perlu.",
      "implementasi_kebijakan_direksi_status": true,
      "proses_pencapaian_kinerja": "Pencapaian kinerja mendekati target, dengan peningkatan volume transaksi.",
      "proses_pencapaian_kinerja_status": true,
      "perbandingan_target_dan_realisasi": "Target transaksi tercapai 90%, realisasi pendapatan 85%.",
      "perbandingan_target_dan_realisasi_status": true,
      "kendala_yang_dihadapi_pjp": "Tantangan dalam adopsi teknologi baru oleh sebagian pelanggan.",
      "kendala_yang_dihadapi_pjp_status": true,
      "tata_kelola_pengawasan_direksi_komisaris": "Pengawasan direksi dan dewan komisaris cukup aktif dan konstruktif.",
      "tata_kelola_pengawasan_direksi_komisaris_status": true,
      "tata_kelola_risiko_sdm": "Manajemen risiko SDM ditingkatkan, dengan fokus pada pelatihan digital.",
      "tata_kelola_risiko_sdm_status": true,
      "tata_kelola_ketersediaan_prosedur": "Prosedur telah disesuaikan dengan perkembangan digital.",
      "tata_kelola_ketersediaan_prosedur_status": true,
      "tata_kelola_pengendalian_intern": "Sistem pengendalian intern terus diperbaiki, dengan audit internal rutin.",
      "tata_kelola_pengendalian_intern_status": true,
      "asesmen_kualitatif_sdm": "Rencana pengembangan SDM berfokus pada skill digital dan analisis data.",
      "asesmen_kualitatif_sdm_status": true,
      "asesmen_kuantitatif_sdm": "Kecukupan SDM memadai, dengan program rekrutmen talenta digital.",
      "asesmen_kuantitatif_sdm_status": true,
      "asesmen_kepemilikan_domestik_asing": "Struktur kepemilikan tidak berubah.",
      "asesmen_kepemilikan_domestik_asing_status": true,
      "asesmen_pengendalian_domestik_asing": "Struktur pengendalian tetap kuat.",
      "asesmen_pengendalian_domestik_asing_status": true,
      "asesmen_pemenuhan_modal": "Permodalan stabil, tidak ada isu signifikan.",
      "asesmen_pemenuhan_modal_status": true,
      "asesmen_manajemen_risiko_it": "Manajemen risiko IT ditingkatkan, dengan fokus pada keamanan siber.",
      "asesmen_manajemen_risiko_it_status": true,
      "pemantauan_kepatuhan": "Pemantauan kepatuhan dilakukan secara rutin, dengan perbaikan berkelanjutan.",
      "pemantauan_kepatuhan_status": true,
      "persentase_kepemilikan_domestik": 100,
      "pengendalian_domestik": 2,
      "persentase_kepemilikan_asing": 0,
      "pengendalian_asing": 0,
      "pihak_pengendali_ubo": "Keluarga Syafitri",
      "keterangan": "Laporan ini menunjukkan upaya Syaftraco dalam beradaptasi dengan perubahan pasar.",
      "file_url": "https://example.com/laporan_manajemen/SFT/2022/LM-SFT-2022-001.pdf",
      "file_path": "laporan_manajemen/SFT/2022/LM-SFT-2022-001.pdf",
      "created_at": "2023-02-15T10:00:00+07:00",
      "manajemen_sign": [
        {
          "nama": "Ir. Budiarto",
          "jabatan": "Komisaris Utama",
          "klasifikasi": "Komisaris"
        },
        {
          "nama": "Dra. Fitriani",
          "jabatan": "Direktur Utama",
          "klasifikasi": "Direksi"
        },
        {
          "nama": "Agus Salim",
          "jabatan": "Direktur Pemasaran",
          "klasifikasi": "Direksi"
        }
      ]
    },
    {
      "sandi_pjp": "777958110",
      "nama_pjp": "PT. Agung Remittance Global",
      "tahun_laporan": 2023,
      "nomor_surat": "LM-ARG-2023-001",
      "tanggal_surat": "2024-01-25",
      "penilaian_perkembangan_industri_sp": "Industri SP global menghadapi ketidakpastian ekonomi.",
      "penilaian_perkembangan_industri_sp_status": true,
      "pengawasan_perkembangan_bisnis_pjp": "Bisnis ARG stabil, namun pertumbuhan melambat.",
      "pengawasan_perkembangan_bisnis_pjp_status": true,
      "pengawasan_tata_kelola_pjp": "Tata kelola perlu diperkuat, terutama dalam kepatuhan regulasi internasional.",
      "pengawasan_tata_kelola_pjp_status": true,
      "pandangan_perbaikan_pjp": "Fokus pada efisiensi biaya dan optimalisasi jaringan.",
      "pandangan_perbaikan_pjp_status": true,
      "perubahan_komposisi_komisaris": "Tidak ada perubahan.",
      "perubahan_komposisi_komisaris_status": false,
      "implementasi_kebijakan_direksi": "Kebijakan direksi berfokus pada konsolidasi dan efisiensi.",
      "implementasi_kebijakan_direksi_status": true,
      "proses_pencapaian_kinerja": "Pencapaian kinerja di bawah target karena kondisi pasar.",
      "proses_pencapaian_kinerja_status": true,
      "perbandingan_target_dan_realisasi": "Target transaksi tercapai 80%, realisasi pendapatan 75%.",
      "perbandingan_target_dan_realisasi_status": true,
      "kendala_yang_dihadapi_pjp": "Tantangan regulasi lintas negara dan fluktuasi nilai tukar.",
      "kendala_yang_dihadapi_pjp_status": true,
      "tata_kelola_pengawasan_direksi_komisaris": "Pengawasan direksi dan dewan komisaris perlu lebih intensif.",
      "tata_kelola_pengawasan_direksi_komisaris_status": true,
      "tata_kelola_risiko_sdm": "Manajemen risiko SDM perlu ditingkatkan, terutama untuk ekspatriat.",
      "tata_kelola_risiko_sdm_status": true,
      "tata_kelola_ketersediaan_prosedur": "Prosedur kepatuhan internasional perlu diperbarui.",
      "tata_kelola_ketersediaan_prosedur_status": true,
      "tata_kelola_pengendalian_intern": "Sistem pengendalian intern perlu audit eksternal untuk kepatuhan global.",
      "tata_kelola_pengendalian_intern_status": true,
      "asesmen_kualitatif_sdm": "Rencana pengembangan SDM untuk kepatuhan global sedang disusun.",
      "asesmen_kualitatif_sdm_status": true,
      "asesmen_kuantitatif_sdm": "Kecukupan SDM memadai, namun perlu peningkatan kompetensi global.",
      "asesmen_kuantitatif_sdm_status": true,
      "asesmen_kepemilikan_domestik_asing": "Struktur kepemilikan stabil, mayoritas asing.",
      "asesmen_kepemilikan_domestik_asing_status": true,
      "asesmen_pengendalian_domestik_asing": "Struktur pengendalian kuat, dengan pengaruh asing yang signifikan.",
      "asesmen_pengendalian_domestik_asing_status": true,
      "asesmen_pemenuhan_modal": "Permodalan memenuhi kewajiban, namun perlu strategi untuk ekspansi global.",
      "asesmen_pemenuhan_modal_status": true,
      "asesmen_manajemen_risiko_it": "Manajemen risiko IT perlu diperkuat untuk transaksi lintas batas.",
      "asesmen_manajemen_risiko_it_status": true,
      "pemantauan_kepatuhan": "Pemantauan kepatuhan terhadap regulasi global perlu ditingkatkan.",
      "pemantauan_kepatuhan_status": true,
      "persentase_kepemilikan_domestik": 20,
      "pengendalian_domestik": 1,
      "persentase_kepemilikan_asing": 80,
      "pengendalian_asing": 2,
      "pihak_pengendali_ubo": "Global Holdings Inc.",
      "keterangan": "Laporan ini menyoroti tantangan dan strategi ARG di pasar global.",
      "file_url": "https://example.com/laporan_manajemen/ARG/2023/LM-ARG-2023-001.pdf",
      "file_path": "laporan_manajemen/ARG/2023/LM-ARG-2023-001.pdf",
      "created_at": "2024-01-30T10:00:00+07:00",
      "manajemen_sign": [
        {
          "nama": "Mr. John Smith",
          "jabatan": "Komisaris Utama",
          "klasifikasi": "Komisaris"
        },
        {
          "nama": "Ms. Jane Doe",
          "jabatan": "Direktur Utama",
          "klasifikasi": "Direksi"
        }
      ]
    },
    {
      "sandi_pjp": "777950113",
      "nama_pjp": "PT. Tiki Jalur Nugraha Ekakurir",
      "tahun_laporan": 2024,
      "nomor_surat": "LM-TJK-2024-001",
      "tanggal_surat": "2025-02-05",
      "penilaian_perkembangan_industri_sp": "Industri SP logistik tumbuh pesat, didorong e-commerce.",
      "penilaian_perkembangan_industri_sp_status": true,
      "pengawasan_perkembangan_bisnis_pjp": "Bisnis TJK sangat baik, volume transaksi meningkat signifikan.",
      "pengawasan_perkembangan_bisnis_pjp_status": true,
      "pengawasan_tata_kelola_pjp": "Tata kelola dan manajemen risiko sangat solid, mendukung ekspansi.",
      "pengawasan_tata_kelola_pjp_status": true,
      "pandangan_perbaikan_pjp": "Perluas jangkauan ke daerah terpencil dan optimalkan teknologi logistik.",
      "pandangan_perbaikan_pjp_status": true,
      "perubahan_komposisi_komisaris": "Tidak ada perubahan.",
      "perubahan_komposisi_komisaris_status": false,
      "implementasi_kebijakan_direksi": "Kebijakan direksi berhasil mendukung pertumbuhan pesat dan efisiensi logistik.",
      "implementasi_kebijakan_direksi_status": true,
      "proses_pencapaian_kinerja": "Pencapaian kinerja melebihi target, dengan peningkatan kepuasan pelanggan.",
      "proses_pencapaian_kinerja_status": true,
      "perbandingan_target_dan_realisasi": "Target pengiriman tercapai 115%, realisasi pendapatan 110%.",
      "perbandingan_target_dan_realisasi_status": true,
      "kendala_yang_dihadapi_pjp": "Infrastruktur jalan yang belum merata di seluruh Indonesia.",
      "kendala_yang_dihadapi_pjp_status": true,
      "tata_kelola_pengawasan_direksi_komisaris": "Pengawasan sangat efektif, mendukung keputusan investasi infrastruktur.",
      "tata_kelola_pengawasan_direksi_komisaris_status": true,
      "tata_kelola_risiko_sdm": "Manajemen risiko SDM fokus pada keselamatan kurir dan efisiensi rute.",
      "tata_kelola_risiko_sdm_status": true,
      "tata_kelola_ketersediaan_prosedur": "Prosedur operasional logistik telah dioptimalkan.",
      "tata_kelola_ketersediaan_prosedur_status": true,
      "tata_kelola_pengendalian_intern": "Sistem pengendalian intern terintegrasi dengan sistem pelacakan logistik.",
      "tata_kelola_pengendalian_intern_status": true,
      "asesmen_kualitatif_sdm": "Rencana pengembangan SDM untuk kurir dan staf logistik berjalan baik.",
      "asesmen_kualitatif_sdm_status": true,
      "asesmen_kuantitatif_sdm": "Kecukupan SDM memadai, dengan program rekrutmen kurir baru.",
      "asesmen_kuantitatif_sdm_status": true,
      "asesmen_kepemilikan_domestik_asing": "Struktur kepemilikan tidak berubah.",
      "asesmen_kepemilikan_domestik_asing_status": true,
      "asesmen_pengendalian_domestik_asing": "Struktur pengendalian tetap kuat.",
      "asesmen_pengendalian_domestik_asing_status": true,
      "asesmen_pemenuhan_modal": "Permodalan sangat kuat, mendukung investasi armada dan teknologi.",
      "asesmen_pemenuhan_modal_status": true,
      "asesmen_manajemen_risiko_it": "Manajemen risiko IT fokus pada keamanan data pelanggan dan sistem logistik.",
      "asesmen_manajemen_risiko_it_status": true,
      "pemantauan_kepatuhan": "Pemantauan kepatuhan terhadap regulasi logistik dan pengiriman.",
      "pemantauan_kepatuhan_status": true,
      "persentase_kepemilikan_domestik": 100,
      "pengendalian_domestik": 3,
      "persentase_kepemilikan_asing": 0,
      "pengendalian_asing": 0,
      "pihak_pengendali_ubo": "PT. Induk TJK",
      "keterangan": "Laporan ini menunjukkan pertumbuhan dan dominasi TJK di sektor logistik SP.",
      "file_url": "https://example.com/laporan_manajemen/TJK/2024/LM-TJK-2024-001.pdf",
      "file_path": "laporan_manajemen/TJK/2024/LM-TJK-2024-001.pdf",
      "created_at": "2025-02-10T10:00:00+07:00",
      "manajemen_sign": [
        {
          "nama": "Dr. Suryo Pranoto",
          "jabatan": "Komisaris Utama",
          "klasifikasi": "Komisaris"
        },
        {
          "nama": "Ir. Citra Dewi",
          "jabatan": "Direktur Utama",
          "klasifikasi": "Direksi"
        },
        {
          "nama": "Wahyu Hidayat",
          "jabatan": "Direktur Logistik",
          "klasifikasi": "Direksi"
        }
      ]
    },
    {
      "sandi_pjp": "777930016",
      "nama_pjp": "PT. VIT Remittance Indonesia",
      "tahun_laporan": 2024,
      "nomor_surat": "LM-VIT-2024-001",
      "tanggal_surat": "2025-02-10",
      "penilaian_perkembangan_industri_sp": "Industri remitansi stabil, namun perlu inovasi untuk menarik generasi muda.",
      "penilaian_perkembangan_industri_sp_status": true,
      "pengawasan_perkembangan_bisnis_pjp": "Bisnis VIT Remittance menunjukkan pertumbuhan moderat, fokus pada layanan digital.",
      "pengawasan_perkembangan_bisnis_pjp_status": true,
      "pengawasan_tata_kelola_pjp": "Tata kelola dan manajemen risiko telah ditingkatkan, sesuai standar internasional.",
      "pengawasan_tata_kelola_pjp_status": true,
      "pandangan_perbaikan_pjp": "Kembangkan aplikasi mobile yang user-friendly dan perluas jaringan agen.",
      "pandangan_perbaikan_pjp_status": true,
      "perubahan_komposisi_komisaris": "Tidak ada perubahan.",
      "perubahan_komposisi_komisaris_status": false,
      "implementasi_kebijakan_direksi": "Kebijakan direksi berhasil mendorong adopsi digital dan peningkatan efisiensi.",
      "implementasi_kebijakan_direksi_status": true,
      "proses_pencapaian_kinerja": "Pencapaian kinerja sesuai target, dengan peningkatan volume transaksi digital.",
      "proses_pencapaian_kinerja_status": true,
      "perbandingan_target_dan_realisasi": "Target transaksi digital tercapai 100%, realisasi ekspansi agen 90%.",
      "perbandingan_target_dan_realisasi_status": true,
      "kendala_yang_dihadapi_pjp": "Persaingan ketat dari platform remitansi berbasis aplikasi.",
      "kendala_yang_dihadapi_pjp_status": true,
      "tata_kelola_pengawasan_direksi_komisaris": "Pengawasan direksi dan dewan komisaris aktif, mendukung inovasi digital.",
      "tata_kelola_pengawasan_direksi_komisaris_status": true,
      "tata_kelola_risiko_sdm": "Manajemen risiko SDM fokus pada pelatihan digital dan kepatuhan AML/CFT.",
      "tata_kelola_risiko_sdm_status": true,
      "tata_kelola_ketersediaan_prosedur": "Prosedur operasional telah disesuaikan untuk layanan digital.",
      "tata_kelola_ketersediaan_prosedur_status": true,
      "tata_kelola_pengendalian_intern": "Sistem pengendalian intern diperkuat untuk transaksi digital.",
      "tata_kelola_pengendalian_intern_status": true,
      "asesmen_kualitatif_sdm": "Rencana pengembangan SDM fokus pada keahlian digital dan kepatuhan.",
      "asesmen_kualitatif_sdm_status": true,
      "asesmen_kuantitatif_sdm": "Kecukupan SDM memadai, dengan program rekrutmen ahli digital.",
      "asesmen_kuantitatif_sdm_status": true,
      "asesmen_kepemilikan_domestik_asing": "Struktur kepemilikan tidak berubah.",
      "asesmen_kepemilikan_domestik_asing_status": true,
      "asesmen_pengendalian_domestik_asing": "Struktur pengendalian tetap kuat.",
      "asesmen_pengendalian_domestik_asing_status": true,
      "asesmen_pemenuhan_modal": "Permodalan kuat, mendukung investasi teknologi.",
      "asesmen_pemenuhan_modal_status": true,
      "asesmen_manajemen_risiko_it": "Manajemen risiko IT fokus pada keamanan aplikasi mobile dan data pelanggan.",
      "asesmen_manajemen_risiko_it_status": true,
      "pemantauan_kepatuhan": "Pemantauan kepatuhan terhadap regulasi remitansi dan AML/CFT.",
      "pemantauan_kepatuhan_status": true,
      "persentase_kepemilikan_domestik": 60,
      "pengendalian_domestik": 2,
      "persentase_kepemilikan_asing": 40,
      "pengendalian_asing": 1,
      "pihak_pengendali_ubo": "Global Remit Group",
      "keterangan": "Laporan ini menunjukkan adaptasi VIT Remittance terhadap tren digital.",
      "file_url": "https://example.com/laporan_manajemen/VIT/2024/LM-VIT-2024-001.pdf",
      "file_path": "laporan_manajemen/VIT/2024/LM-VIT-2024-001.pdf",
      "created_at": "2025-02-15T10:00:00+07:00",
      "manajemen_sign": [
        {
          "nama": "Mr. David Lee",
          "jabatan": "Komisaris Utama",
          "klasifikasi": "Komisaris"
        },
        {
          "nama": "Ms. Sarah Chen",
          "jabatan": "Direktur Utama",
          "klasifikasi": "Direksi"
        }
      ]
    },
    {
      "sandi_pjp": "777930018",
      "nama_pjp": "PT. Madame Express Remitindo",
      "tahun_laporan": 2023,
      "nomor_surat": "LM-MER-2023-001",
      "tanggal_surat": "2024-01-28",
      "penilaian_perkembangan_industri_sp": "Industri remitansi mulai pulih, namun masih ada dampak pandemi.",
      "penilaian_perkembangan_industri_sp_status": true,
      "pengawasan_perkembangan_bisnis_pjp": "Bisnis MER menunjukkan tanda-tanda pemulihan, fokus pada efisiensi.",
      "pengawasan_perkembangan_bisnis_pjp_status": true,
      "pengawasan_tata_kelola_pjp": "Tata kelola perlu diperkuat untuk menghadapi volatilitas pasar.",
      "pengawasan_tata_kelola_pjp_status": true,
      "pandangan_perbaikan_pjp": "Optimalkan jaringan agen dan tingkatkan layanan pelanggan.",
      "pandangan_perbaikan_pjp_status": true,
      "perubahan_komposisi_komisaris": "Tidak ada perubahan.",
      "perubahan_komposisi_komisaris_status": false,
      "implementasi_kebijakan_direksi": "Kebijakan direksi berfokus pada pemulihan dan stabilitas operasional.",
      "implementasi_kebijakan_direksi_status": true,
      "proses_pencapaian_kinerja": "Pencapaian kinerja menunjukkan perbaikan, namun masih di bawah target.",
      "proses_pencapaian_kinerja_status": true,
      "perbandingan_target_dan_realisasi": "Target transaksi tercapai 65%, realisasi pendapatan 60%.",
      "perbandingan_target_dan_realisasi_status": true,
      "kendala_yang_dihadapi_pjp": "Pembatasan perjalanan dan perubahan perilaku konsumen.",
      "kendala_yang_dihadapi_pjp_status": true,
      "tata_kelola_pengawasan_direksi_komisaris": "Pengawasan direksi dan dewan komisaris aktif, fokus pada strategi pemulihan.",
      "tata_kelola_pengawasan_direksi_komisaris_status": true,
      "tata_kelola_risiko_sdm": "Manajemen risiko SDM fokus pada kesejahteraan karyawan dan pelatihan digital.",
      "tata_kelola_risiko_sdm_status": true,
      "tata_kelola_ketersediaan_prosedur": "Prosedur untuk layanan digital baru telah disusun.",
      "tata_kelola_ketersediaan_prosedur_status": true,
      "tata_kelola_pengendalian_intern": "Sistem pengendalian intern diperbarui untuk mendukung operasional hibrida.",
      "tata_kelola_pengendalian_intern_status": true,
      "asesmen_kualitatif_sdm": "Rencana pengembangan SDM fokus pada keahlian digital dan adaptasi.",
      "asesmen_kualitatif_sdm_status": true,
      "asesmen_kuantitatif_sdm": "Kecukupan SDM memadai, dengan penyesuaian jumlah karyawan.",
      "asesmen_kuantitatif_sdm_status": true,
      "asesmen_kepemilikan_domestik_asing": "Struktur kepemilikan stabil.",
      "asesmen_kepemilikan_domestik_asing_status": true,
      "asesmen_pengendalian_domestik_asing": "Struktur pengendalian tetap kuat.",
      "asesmen_pengendalian_domestik_asing_status": true,
      "asesmen_pemenuhan_modal": "Permodalan stabil, namun perlu strategi untuk pertumbuhan berkelanjutan.",
      "asesmen_pemenuhan_modal_status": true,
      "asesmen_manajemen_risiko_it": "Manajemen risiko IT fokus pada keamanan platform digital dan data transaksi.",
      "asesmen_manajemen_risiko_it_status": true,
      "pemantauan_kepatuhan": "Pemantauan kepatuhan terhadap regulasi global dan digital.",
      "pemantauan_kepatuhan_status": true,
      "persentase_kepemilikan_domestik": 50,
      "pengendalian_domestik": 1,
      "persentase_kepemilikan_asing": 50,
      "pengendalian_asing": 1,
      "pihak_pengendali_ubo": "Global Remit Corp.",
      "keterangan": "Laporan ini menunjukkan upaya pemulihan MER di pasar global.",
      "file_url": "https://example.com/laporan_manajemen/MER/2023/LM-MER-2023-001.pdf",
      "file_path": "laporan_manajemen/MER/2023/LM-MER-2023-001.pdf",
      "created_at": "2024-02-01T10:00:00+07:00",
      "manajemen_sign": [
        {
          "nama": "Mr. Robert Johnson",
          "jabatan": "Komisaris Utama",
          "klasifikasi": "Komisaris"
        },
        {
          "nama": "Ms. Emily White",
          "jabatan": "Direktur Utama",
          "klasifikasi": "Direksi"
        }
      ]
    },
    {
      "sandi_pjp": "777930026",
      "nama_pjp": "PT. EMQ Indonesia Asia",
      "tahun_laporan": 2024,
      "nomor_surat": "LM-EMQ-2024-001",
      "tanggal_surat": "2025-02-15",
      "penilaian_perkembangan_industri_sp": "Industri SP Asia Tenggara sangat kompetitif, didorong inovasi.",
      "penilaian_perkembangan_industri_sp_status": true,
      "pengawasan_perkembangan_bisnis_pjp": "Bisnis EMQ tumbuh pesat, fokus pada ekspansi regional.",
      "pengawasan_perkembangan_bisnis_pjp_status": true,
      "pengawasan_tata_kelola_pjp": "Tata kelola dan manajemen risiko sangat kuat, mendukung pertumbuhan agresif.",
      "pengawasan_tata_kelola_pjp_status": true,
      "pandangan_perbaikan_pjp": "Perkuat kemitraan strategis dan tingkatkan penetrasi pasar.",
      "pandangan_perbaikan_pjp_status": true,
      "perubahan_komposisi_komisaris": "Tidak ada perubahan.",
      "perubahan_komposisi_komisaris_status": false,
      "implementasi_kebijakan_direksi": "Kebijakan direksi berhasil mendukung ekspansi dan inovasi produk.",
      "implementasi_kebijakan_direksi_status": true,
      "proses_pencapaian_kinerja": "Pencapaian kinerja melebihi target, dengan peningkatan pangsa pasar.",
      "proses_pencapaian_kinerja_status": true,
      "perbandingan_target_dan_realisasi": "Target pengguna baru tercapai 120%, realisasi pendapatan 115%.",
      "perbandingan_target_dan_realisasi_status": true,
      "kendala_yang_dihadapi_pjp": "Perbedaan regulasi di setiap negara Asia Tenggara.",
      "kendala_yang_dihadapi_pjp_status": true,
      "tata_kelola_pengawasan_direksi_komisaris": "Pengawasan direksi dan dewan komisaris sangat strategis, mendukung ekspansi regional.",
      "tata_kelola_pengawasan_direksi_komisaris_status": true,
      "tata_kelola_risiko_sdm": "Manajemen risiko SDM fokus pada rekrutmen talenta lintas negara.",
      "tata_kelola_risiko_sdm_status": true,
      "tata_kelola_ketersediaan_prosedur": "Prosedur operasional telah disesuaikan untuk skala regional.",
      "tata_kelola_ketersediaan_prosedur_status": true,
      "tata_kelola_pengendalian_intern": "Sistem pengendalian intern terintegrasi di seluruh operasi regional.",
      "tata_kelola_pengendalian_intern_status": true,
      "asesmen_kualitatif_sdm": "Rencana pengembangan SDM fokus pada keahlian lintas budaya dan kepatuhan regional.",
      "asesmen_kualitatif_sdm_status": true,
      "asesmen_kuantitatif_sdm": "Kecukupan SDM memadai, dengan program rekrutmen regional.",
      "asesmen_kuantitatif_sdm_status": true,
      "asesmen_kepemilikan_domestik_asing": "Struktur kepemilikan tidak berubah.",
      "asesmen_kepemilikan_domestik_asing_status": true,
      "asesmen_pengendalian_domestik_asing": "Struktur pengendalian kuat, mendukung operasi regional.",
      "asesmen_pengendalian_domestik_asing_status": true,
      "asesmen_pemenuhan_modal": "Permodalan sangat kuat, mendukung ekspansi regional.",
      "asesmen_pemenuhan_modal_status": true,
      "asesmen_manajemen_risiko_it": "Manajemen risiko IT fokus pada keamanan data lintas batas dan integrasi sistem.",
      "asesmen_manajemen_risiko_it_status": true,
      "pemantauan_kepatuhan": "Pemantauan kepatuhan terhadap regulasi di berbagai negara Asia Tenggara.",
      "pemantauan_kepatuhan_status": true,
      "persentase_kepemilikan_domestik": 30,
      "pengendalian_domestik": 1,
      "persentase_kepemilikan_asing": 70,
      "pengendalian_asing": 2,
      "pihak_pengendali_ubo": "Asia Fintech Group",
      "keterangan": "Laporan ini menunjukkan pertumbuhan dan ambisi EMQ di pasar Asia Tenggara.",
      "file_url": "https://example.com/laporan_manajemen/EMQ/2024/LM-EMQ-2024-001.pdf",
      "file_path": "laporan_manajemen/EMQ/2024/LM-EMQ-2024-001.pdf",
      "created_at": "2025-02-20T10:00:00+07:00",
      "manajemen_sign": [
        {
          "nama": "Mr. Kenji Tanaka",
          "jabatan": "Komisaris Utama",
          "klasifikasi": "Komisaris"
        },
        {
          "nama": "Ms. Li Wei",
          "jabatan": "Direktur Utama",
          "klasifikasi": "Direksi"
        },
        {
          "nama": "Mr. Alex Wong",
          "jabatan": "Direktur Pengembangan Bisnis",
          "klasifikasi": "Direksi"
        }
      ]
    },
    {
      "sandi_pjp": "777950114",
      "nama_pjp": "PT. Pacto",
      "tahun_laporan": 2023,
      "nomor_surat": "LM-PACTO-2023-001",
      "tanggal_surat": "2024-02-20",
      "penilaian_perkembangan_industri_sp": "Industri SP pariwisata mulai bangkit, namun masih fluktuatif.",
      "penilaian_perkembangan_industri_sp_status": true,
      "pengawasan_perkembangan_bisnis_pjp": "Bisnis Pacto menunjukkan pemulihan, fokus pada adaptasi model bisnis.",
      "pengawasan_perkembangan_bisnis_pjp_status": true,
      "pengawasan_tata_kelola_pjp": "Tata kelola perlu diperkuat dalam menghadapi ketidakpastian pasar.",
      "pengawasan_tata_kelola_pjp_status": true,
      "pandangan_perbaikan_pjp": "Diversifikasi layanan di luar pariwisata dan efisiensi operasional.",
      "pandangan_perbaikan_pjp_status": true,
      "perubahan_komposisi_komisaris": "Tidak ada perubahan.",
      "perubahan_komposisi_komisaris_status": false,
      "implementasi_kebijakan_direksi": "Kebijakan direksi berfokus pada pemulihan dan inovasi layanan.",
      "implementasi_kebijakan_direksi_status": true,
      "proses_pencapaian_kinerja": "Pencapaian kinerja di bawah target, namun ada perbaikan di paruh kedua tahun.",
      "proses_pencapaian_kinerja_status": true,
      "perbandingan_target_dan_realisasi": "Target pendapatan tercapai 60%, realisasi jumlah transaksi 55%.",
      "perbandingan_target_dan_realisasi_status": true,
      "kendala_yang_dihadapi_pjp": "Pembatasan perjalanan internasional dan perubahan preferensi konsumen.",
      "kendala_yang_dihadapi_pjp_status": true,
      "tata_kelola_pengawasan_direksi_komisaris": "Pengawasan direksi dan dewan komisaris cukup, perlu lebih adaptif.",
      "tata_kelola_pengawasan_direksi_komisaris_status": true,
      "tata_kelola_risiko_sdm": "Manajemen risiko SDM fokus pada fleksibilitas kerja dan pelatihan ulang.",
      "tata_kelola_risiko_sdm_status": true,
      "tata_kelola_ketersediaan_prosedur": "Prosedur untuk layanan baru sedang disusun.",
      "tata_kelola_ketersediaan_prosedur_status": true,
      "tata_kelola_pengendalian_intern": "Sistem pengendalian intern perlu diperbarui untuk model bisnis hibrida.",
      "tata_kelola_pengendalian_intern_status": true,
      "asesmen_kualitatif_sdm": "Rencana pengembangan SDM fokus pada keahlian digital dan layanan pelanggan.",
      "asesmen_kualitatif_sdm_status": true,
      "asesmen_kuantitatif_sdm": "Kecukupan SDM memadai, dengan penyesuaian jumlah karyawan.",
      "asesmen_kuantitatif_sdm_status": true,
      "asesmen_kepemilikan_domestik_asing": "Struktur kepemilikan tidak berubah.",
      "asesmen_kepemilikan_domestik_asing_status": true,
      "asesmen_pengendalian_domestik_asing": "Struktur pengendalian tetap kuat.",
      "asesmen_pengendalian_domestik_asing_status": true,
      "asesmen_pemenuhan_modal": "Permodalan stabil, namun perlu strategi untuk pertumbuhan berkelanjutan.",
      "asesmen_pemenuhan_modal_status": true,
      "asesmen_manajemen_risiko_it": "Manajemen risiko IT fokus pada keamanan platform online dan data transaksi.",
      "asesmen_manajemen_risiko_it_status": true,
      "pemantauan_kepatuhan": "Pemantauan kepatuhan terhadap regulasi pariwisata dan pembayaran.",
      "pemantauan_kepatuhan_status": true,
      "persentase_kepemilikan_domestik": 90,
      "pengendalian_domestik": 2,
      "persentase_kepemilikan_asing": 10,
      "pengendalian_asing": 0,
      "pihak_pengendali_ubo": "Pacto Group",
      "keterangan": "Laporan ini menggambarkan upaya Pacto dalam menghadapi tantangan dan peluang di sektor pariwisata.",
      "file_url": "https://example.com/laporan_manajemen/PACTO/2023/LM-PACTO-2023-001.pdf",
      "file_path": "laporan_manajemen/PACTO/2023/LM-PACTO-2023-001.pdf",
      "created_at": "2024-02-25T10:00:00+07:00",
      "manajemen_sign": [
        {
          "nama": "Mr. Adi Susanto",
          "jabatan": "Komisaris Utama",
          "klasifikasi": "Komisaris"
        },
        {
          "nama": "Ms. Rina Wati",
          "jabatan": "Direktur Utama",
          "klasifikasi": "Direksi"
        }
      ]
    },
    {
      "sandi_pjp": "777958115",
      "nama_pjp": "PT. Eka Bakti Amerta Yoga Sejahtera",
      "tahun_laporan": 2024,
      "nomor_surat": "LM-EBA-2024-001",
      "tanggal_surat": "2025-02-25",
      "penilaian_perkembangan_industri_sp": "Industri SP kesehatan dan kesejahteraan menunjukkan potensi besar.",
      "penilaian_perkembangan_industri_sp_status": true,
      "pengawasan_perkembangan_bisnis_pjp": "Bisnis EBA tumbuh stabil, fokus pada perluasan ekosistem digital kesehatan.",
      "pengawasan_perkembangan_bisnis_pjp_status": true,
      "pengawasan_tata_kelola_pjp": "Tata kelola dan manajemen risiko sangat kuat, mendukung inovasi di sektor kesehatan.",
      "pengawasan_tata_kelola_pjp_status": true,
      "pandangan_perbaikan_pjp": "Integrasi lebih lanjut dengan penyedia layanan kesehatan dan asuransi.",
      "pandangan_perbaikan_pjp_status": true,
      "perubahan_komposisi_komisaris": "Tidak ada perubahan.",
      "perubahan_komposisi_komisaris_status": false,
      "implementasi_kebijakan_direksi": "Kebijakan direksi berhasil mendorong pertumbuhan di sektor kesehatan digital.",
      "implementasi_kebijakan_direksi_status": true,
      "proses_pencapaian_kinerja": "Pencapaian kinerja melebihi target, dengan peningkatan jumlah pengguna aktif.",
      "proses_pencapaian_kinerja_status": true,
      "perbandingan_target_dan_realisasi": "Target pengguna tercapai 110%, realisasi kemitraan 105%.",
      "perbandingan_target_dan_realisasi_status": true,
      "kendala_yang_dihadapi_pjp": "Regulasi yang kompleks di sektor kesehatan dan privasi data medis.",
      "kendala_yang_dihadapi_pjp_status": true,
      "tata_kelola_pengawasan_direksi_komisaris": "Pengawasan direksi dan dewan komisaris sangat strategis, fokus pada kepatuhan regulasi kesehatan.",
      "tata_kelola_pengawasan_direksi_komisaris_status": true,
      "tata_kelola_risiko_sdm": "Manajemen risiko SDM fokus pada pelatihan kepatuhan data medis dan etika.",
      "tata_kelola_risiko_sdm_status": true,
      "tata_kelola_ketersediaan_prosedur": "Prosedur untuk penanganan data medis dan privasi telah diimplementasikan.",
      "tata_kelola_ketersediaan_prosedur_status": true,
      "tata_kelola_pengendalian_intern": "Sistem pengendalian intern diperkuat untuk melindungi data medis sensitif.",
      "tata_kelola_pengendalian_intern_status": true,
      "asesmen_kualitatif_sdm": "Rencana pengembangan SDM fokus pada keahlian di bidang kesehatan digital dan privasi data.",
      "asesmen_kualitatif_sdm_status": true,
      "asesmen_kuantitatif_sdm": "Kecukupan SDM memadai, dengan program rekrutmen ahli kesehatan.",
      "asesmen_kuantitatif_sdm_status": true,
      "asesmen_kepemilikan_domestik_asing": "Struktur kepemilikan tidak berubah.",
      "asesmen_kepemilikan_domestik_asing_status": true,
      "asesmen_pengendalian_domestik_asing": "Struktur pengendalian tetap kuat.",
      "asesmen_pengendalian_domestik_asing_status": true,
      "asesmen_pemenuhan_modal": "Permodalan sangat kuat, mendukung investasi di sektor kesehatan.",
      "asesmen_pemenuhan_modal_status": true,
      "asesmen_manajemen_risiko_it": "Manajemen risiko IT fokus pada keamanan dan privasi data medis.",
      "asesmen_manajemen_risiko_it_status": true,
      "pemantauan_kepatuhan": "Pemantauan kepatuhan terhadap regulasi kesehatan dan privasi data sangat ketat.",
      "pemantauan_kepatuhan_status": true,
      "persentase_kepemilikan_domestik": 95,
      "pengendalian_domestik": 3,
      "persentase_kepemilikan_asing": 5,
      "pengendalian_asing": 0,
      "pihak_pengendali_ubo": "Eka Bakti Group",
      "keterangan": "Laporan ini menunjukkan komitmen EBA terhadap inovasi di sektor kesehatan digital.",
      "file_url": "https://example.com/laporan_manajemen/EBA/2024/LM-EBA-2024-001.pdf",
      "file_path": "laporan_manajemen/EBA/2024/LM-EBA-2024-001.pdf",
      "created_at": "2025-03-01T10:00:00+07:00",
      "manajemen_sign": [
        {
          "nama": "Dr. Ratna Sari",
          "jabatan": "Komisaris Utama",
          "klasifikasi": "Komisaris"
        },
        {
          "nama": "Prof. Bayu Putra",
          "jabatan": "Direktur Utama",
          "klasifikasi": "Direksi"
        }
      ]
    },
    {
      "sandi_pjp": "777953739",
      "nama_pjp": "PT. Indomarco Prismatama",
      "tahun_laporan": 2023,
      "nomor_surat": "LM-IND-2023-001",
      "tanggal_surat": "2024-03-10",
      "penilaian_perkembangan_industri_sp": "Industri SP ritel terus tumbuh, didorong oleh belanja konsumen dan digitalisasi.",
      "penilaian_perkembangan_industri_sp_status": true,
      "pengawasan_perkembangan_bisnis_pjp": "Bisnis Indomarco tumbuh kuat, fokus pada integrasi online-offline.",
      "pengawasan_perkembangan_bisnis_pjp_status": true,
      "pengawasan_tata_kelola_pjp": "Tata kelola dan manajemen risiko sangat solid, mendukung pertumbuhan berkelanjutan.",
      "pengawasan_tata_kelola_pjp_status": true,
      "pandangan_perbaikan_pjp": "Perluas layanan pembayaran digital di gerai fisik dan online.",
      "pandangan_perbaikan_pjp_status": true,
      "perubahan_komposisi_komisaris": "Tidak ada perubahan.",
      "perubahan_komposisi_komisaris_status": false,
      "implementasi_kebijakan_direksi": "Kebijakan direksi berhasil mendorong pertumbuhan penjualan dan efisiensi operasional.",
      "implementasi_kebijakan_direksi_status": true,
      "proses_pencapaian_kinerja": "Pencapaian kinerja melebihi target, dengan peningkatan loyalitas pelanggan.",
      "proses_pencapaian_kinerja_status": true,
      "perbandingan_target_dan_realisasi": "Target penjualan tercapai 110%, realisasi ekspansi gerai 100%.",
      "perbandingan_target_dan_realisasi_status": true,
      "kendala_yang_dihadapi_pjp": "Inflasi dan kenaikan harga bahan baku.",
      "kendala_yang_dihadapi_pjp_status": true,
      "tata_kelola_pengawasan_direksi_komisaris": "Pengawasan direksi dan dewan komisaris aktif, mendukung keputusan investasi.",
      "tata_kelola_pengawasan_direksi_komisaris_status": true,
      "tata_kelola_risiko_sdm": "Manajemen risiko SDM fokus pada retensi karyawan dan pelatihan layanan pelanggan.",
      "tata_kelola_risiko_sdm_status": true,
      "tata_kelola_ketersediaan_prosedur": "Prosedur operasional standar telah dioptimalkan untuk efisiensi.",
      "tata_kelola_ketersediaan_prosedur_status": true,
      "tata_kelola_pengendalian_intern": "Sistem pengendalian intern terintegrasi dengan sistem POS dan inventori.",
      "tata_kelola_pengendalian_intern_status": true,
      "asesmen_kualitatif_sdm": "Rencana pengembangan SDM fokus pada keahlian ritel dan layanan pelanggan.",
      "asesmen_kualitatif_sdm_status": true,
      "asesmen_kuantitatif_sdm": "Kecukupan SDM memadai, dengan program rekrutmen staf gerai.",
      "asesmen_kuantitatif_sdm_status": true,
      "asesmen_kepemilikan_domestik_asing": "Struktur kepemilikan tidak berubah.",
      "asesmen_kepemilikan_domestik_asing_status": true,
      "asesmen_pengendalian_domestik_asing": "Struktur pengendalian tetap kuat.",
      "asesmen_pengendalian_domestik_asing_status": true,
      "asesmen_pemenuhan_modal": "Permodalan sangat kuat, mendukung ekspansi dan investasi.",
      "asesmen_pemenuhan_modal_status": true,
      "asesmen_manajemen_risiko_it": "Manajemen risiko IT fokus pada keamanan transaksi dan data pelanggan.",
      "asesmen_manajemen_risiko_it_status": true,
      "pemantauan_kepatuhan": "Pemantauan kepatuhan terhadap regulasi ritel dan pembayaran.",
      "pemantauan_kepatuhan_status": true,
      "persentase_kepemilikan_domestik": 100,
      "pengendalian_domestik": 4,
      "persentase_kepemilikan_asing": 0,
      "pengendalian_asing": 0,
      "pihak_pengendali_ubo": "Salim Group",
      "keterangan": "Laporan ini menunjukkan pertumbuhan dan dominasi Indomarco di sektor ritel SP.",
      "file_url": "https://example.com/laporan_manajemen/IND/2023/LM-IND-2023-001.pdf",
      "file_path": "laporan_manajemen/IND/2023/LM-IND-2023-001.pdf",
      "created_at": "2024-03-15T10:00:00+07:00",
      "manajemen_sign": [
        {
          "nama": "Mr. Anthony Salim",
          "jabatan": "Komisaris Utama",
          "klasifikasi": "Komisaris"
        },
        {
          "nama": "Mr. Hendra Wijaya",
          "jabatan": "Direktur Utama",
          "klasifikasi": "Direksi"
        }
      ]
    },
    {
      "sandi_pjp": "777958116",
      "nama_pjp": "PT. VIP Remittance",
      "tahun_laporan": 2024,
      "nomor_surat": "LM-VIP-2024-001",
      "tanggal_surat": "2025-03-05",
      "penilaian_perkembangan_industri_sp": "Industri remitansi stabil, namun perlu inovasi untuk menarik generasi muda.",
      "penilaian_perkembangan_industri_sp_status": true,
      "pengawasan_perkembangan_bisnis_pjp": "Bisnis VIP Remittance menunjukkan pertumbuhan moderat, fokus pada layanan digital.",
      "pengawasan_perkembangan_bisnis_pjp_status": true,
      "pengawasan_tata_kelola_pjp": "Tata kelola dan manajemen risiko telah ditingkatkan, sesuai standar internasional.",
      "pengawasan_tata_kelola_pjp_status": true,
      "pandangan_perbaikan_pjp": "Kembangkan aplikasi mobile yang user-friendly dan perluas jaringan agen.",
      "pandangan_perbaikan_pjp_status": true,
      "perubahan_komposisi_komisaris": "Tidak ada perubahan.",
      "perubahan_komposisi_komisaris_status": false,
      "implementasi_kebijakan_direksi": "Kebijakan direksi berhasil mendorong adopsi digital dan peningkatan efisiensi.",
      "implementasi_kebijakan_direksi_status": true,
      "proses_pencapaian_kinerja": "Pencapaian kinerja sesuai target, dengan peningkatan volume transaksi digital.",
      "proses_pencapaian_kinerja_status": true,
      "perbandingan_target_dan_realisasi": "Target transaksi digital tercapai 100%, realisasi ekspansi agen 90%.",
      "perbandingan_target_dan_realisasi_status": true,
      "kendala_yang_dihadapi_pjp": "Persaingan ketat dari platform remitansi berbasis aplikasi.",
      "kendala_yang_dihadapi_pjp_status": true,
      "tata_kelola_pengawasan_direksi_komisaris": "Pengawasan direksi dan dewan komisaris aktif, mendukung inovasi digital.",
      "tata_kelola_pengawasan_direksi_komisaris_status": true,
      "tata_kelola_risiko_sdm": "Manajemen risiko SDM fokus pada pelatihan digital dan kepatuhan AML/CFT.",
      "tata_kelola_risiko_sdm_status": true,
      "tata_kelola_ketersediaan_prosedur": "Prosedur operasional telah disesuaikan untuk layanan digital.",
      "tata_kelola_ketersediaan_prosedur_status": true,
      "tata_kelola_pengendalian_intern": "Sistem pengendalian intern diperkuat untuk transaksi digital.",
      "tata_kelola_pengendalian_intern_status": true,
      "asesmen_kualitatif_sdm": "Rencana pengembangan SDM fokus pada keahlian digital dan kepatuhan.",
      "asesmen_kualitatif_sdm_status": true,
      "asesmen_kuantitatif_sdm": "Kecukupan SDM memadai, dengan program rekrutmen ahli digital.",
      "asesmen_kuantitatif_sdm_status": true,
      "asesmen_kepemilikan_domestik_asing": "Struktur kepemilikan tidak berubah.",
      "asesmen_kepemilikan_domestik_asing_status": true,
      "asesmen_pengendalian_domestik_asing": "Struktur pengendalian tetap kuat.",
      "asesmen_pengendalian_domestik_asing_status": true,
      "asesmen_pemenuhan_modal": "Permodalan kuat, mendukung investasi teknologi.",
      "asesmen_pemenuhan_modal_status": true,
      "asesmen_manajemen_risiko_it": "Manajemen risiko IT fokus pada keamanan aplikasi mobile dan data pelanggan.",
      "asesmen_manajemen_risiko_it_status": true,
      "pemantauan_kepatuhan": "Pemantauan kepatuhan terhadap regulasi remitansi dan AML/CFT.",
      "pemantauan_kepatuhan_status": true,
      "persentase_kepemilikan_domestik": 60,
      "pengendalian_domestik": 2,
      "persentase_kepemilikan_asing": 40,
      "pengendalian_asing": 1,
      "pihak_pengendali_ubo": "Global Remit Group",
      "keterangan": "Laporan ini menunjukkan adaptasi VIP Remittance terhadap tren digital.",
      "file_url": "https://example.com/laporan_manajemen/VIP/2024/LM-VIP-2024-001.pdf",
      "file_path": "laporan_manajemen/VIP/2024/LM-VIP-2024-001.pdf",
      "created_at": "2025-03-10T10:00:00+07:00",
      "manajemen_sign": [
        {
          "nama": "Mr. David Lee",
          "jabatan": "Komisaris Utama",
          "klasifikasi": "Komisaris"
        },
        {
          "nama": "Ms. Sarah Chen",
          "jabatan": "Direktur Utama",
          "klasifikasi": "Direksi"
        }
      ]
    },
    {
      "sandi_pjp": "777958118",
      "nama_pjp": "PT. Dhasatra Moneytransfer)",
      "tahun_laporan": 2023,
      "nomor_surat": "LM-DHA-2023-001",
      "tanggal_surat": "2024-03-10",
      "penilaian_perkembangan_industri_sp": "Industri money transfer menghadapi tantangan regulasi dan persaingan.",
      "penilaian_perkembangan_industri_sp_status": true,
      "pengawasan_perkembangan_bisnis_pjp": "Bisnis Dhasatra stabil, namun perlu peningkatan efisiensi operasional.",
      "pengawasan_perkembangan_bisnis_pjp_status": true,
      "pengawasan_tata_kelola_pjp": "Tata kelola perlu diperkuat, terutama dalam kepatuhan AML/CFT.",
      "pengawasan_tata_kelola_pjp_status": true,
      "pandangan_perbaikan_pjp": "Otomatisasi proses dan peningkatan pelatihan kepatuhan.",
      "pandangan_perbaikan_pjp_status": true,
      "perubahan_komposisi_komisaris": "Tidak ada perubahan.",
      "perubahan_komposisi_komisaris_status": false,
      "implementasi_kebijakan_direksi": "Kebijakan direksi berfokus pada kepatuhan dan efisiensi.",
      "implementasi_kebijakan_direksi_status": true,
      "proses_pencapaian_kinerja": "Pencapaian kinerja sesuai target, dengan peningkatan kepatuhan.",
      "proses_pencapaian_kinerja_status": true,
      "perbandingan_target_dan_realisasi": "Target kepatuhan tercapai 95%, realisasi efisiensi 90%.",
      "perbandingan_target_dan_realisasi_status": true,
      "kendala_yang_dihadapi_pjp": "Peningkatan biaya kepatuhan dan kompleksitas regulasi.",
      "kendala_yang_dihadapi_pjp_status": true,
      "tata_kelola_pengawasan_direksi_komisaris": "Pengawasan direksi dan dewan komisaris aktif, fokus pada kepatuhan.",
      "tata_kelola_pengawasan_direksi_komisaris_status": true,
      "tata_kelola_risiko_sdm": "Manajemen risiko SDM fokus pada pelatihan AML/CFT dan etika.",
      "tata_kelola_risiko_sdm_status": true,
      "tata_kelola_ketersediaan_prosedur": "Prosedur kepatuhan telah diperbarui dan diimplementasikan.",
      "tata_kelola_ketersediaan_prosedur_status": true,
      "tata_kelola_pengendalian_intern": "Sistem pengendalian intern diperkuat untuk deteksi transaksi mencurigakan.",
      "tata_kelola_pengendalian_intern_status": true,
      "asesmen_kualitatif_sdm": "Rencana pengembangan SDM fokus pada keahlian kepatuhan dan analisis risiko.",
      "asesmen_kualitatif_sdm_status": true,
      "asesmen_kuantitatif_sdm": "Kecukupan SDM memadai, dengan program pelatihan kepatuhan.",
      "asesmen_kuantitatif_sdm_status": true,
      "asesmen_kepemilikan_domestik_asing": "Struktur kepemilikan tidak berubah.",
      "asesmen_kepemilikan_domestik_asing_status": true,
      "asesmen_pengendalian_domestik_asing": "Struktur pengendalian tetap kuat.",
      "asesmen_pengendalian_domestik_asing_status": true,
      "asesmen_pemenuhan_modal": "Permodalan kuat, mendukung investasi kepatuhan.",
      "asesmen_pemenuhan_modal_status": true,
      "asesmen_manajemen_risiko_it": "Manajemen risiko IT fokus pada keamanan sistem money transfer dan data pelanggan.",
      "asesmen_manajemen_risiko_it_status": true,
      "pemantauan_kepatuhan": "Pemantauan kepatuhan sangat ketat terhadap regulasi AML/CFT.",
      "pemantauan_kepatuhan_status": true,
      "persentase_kepemilikan_domestik": 80,
      "pengendalian_domestik": 2,
      "persentase_kepemilikan_asing": 20,
      "pengendalian_asing": 1,
      "pihak_pengendali_ubo": "Dhasatra Group",
      "keterangan": "Laporan ini menunjukkan komitmen Dhasatra terhadap kepatuhan dan keamanan.",
      "file_url": "https://example.com/laporan_manajemen/DHA/2023/LM-DHA-2023-001.pdf",
      "file_path": "laporan_manajemen/DHA/2023/LM-DHA-2023-001.pdf",
      "created_at": "2024-03-15T10:00:00+07:00",
      "manajemen_sign": [
        {
          "nama": "Mr. Chandra Utama",
          "jabatan": "Komisaris Utama",
          "klasifikasi": "Komisaris"
        },
        {
          "nama": "Ms. Diana Putri",
          "jabatan": "Direktur Utama",
          "klasifikasi": "Direksi"
        }
      ]
    },
    {
      "sandi_pjp": "777958117",
      "nama_pjp": "PT. Priority Valasindo Remittance (d/h Sdr. Suwandi)",
      "tahun_laporan": 2024,
      "nomor_surat": "LM-PVR-2024-001",
      "tanggal_surat": "2025-03-15",
      "penilaian_perkembangan_industri_sp": "Industri valas dan remitansi menunjukkan pertumbuhan signifikan.",
      "penilaian_perkembangan_industri_sp_status": true,
      "pengawasan_perkembangan_bisnis_pjp": "Bisnis PVR tumbuh pesat, fokus pada layanan premium dan korporasi.",
      "pengawasan_perkembangan_bisnis_pjp_status": true,
      "pengawasan_tata_kelola_pjp": "Tata kelola dan manajemen risiko sangat kuat, mendukung pertumbuhan agresif.",
      "pengawasan_tata_kelola_pjp_status": true,
      "pandangan_perbaikan_pjp": "Perluas layanan konsultasi valas dan integrasi API untuk bisnis.",
      "pandangan_perbaikan_pjp_status": true,
      "perubahan_komposisi_komisaris": "Tidak ada perubahan.",
      "perubahan_komposisi_komisaris_status": false,
      "implementasi_kebijakan_direksi": "Kebijakan direksi berhasil mendorong pertumbuhan dan diversifikasi layanan.",
      "implementasi_kebijakan_direksi_status": true,
      "proses_pencapaian_kinerja": "Pencapaian kinerja melebihi target, dengan peningkatan volume transaksi valas.",
      "proses_pencapaian_kinerja_status": true,
      "perbandingan_target_dan_realisasi": "Target volume transaksi tercapai 110%, realisasi pendapatan 105%.",
      "perbandingan_target_dan_realisasi_status": true,
      "kendala_yang_dihadapi_pjp": "Volatilitas pasar valuta asing global.",
      "kendala_yang_dihadapi_pjp_status": true,
      "tata_kelola_pengawasan_direksi_komisaris": "Pengawasan direksi dan dewan komisaris sangat strategis, fokus pada risiko pasar.",
      "tata_kelola_pengawasan_direksi_komisaris_status": true,
      "tata_kelola_risiko_sdm": "Manajemen risiko SDM fokus pada pelatihan analisis pasar dan kepatuhan.",
      "tata_kelola_risiko_sdm_status": true,
      "tata_kelola_ketersediaan_prosedur": "Prosedur untuk transaksi valas kompleks telah dioptimalkan.",
      "tata_kelola_ketersediaan_prosedur_status": true,
      "tata_kelola_pengendalian_intern": "Sistem pengendalian intern diperkuat untuk memitigasi risiko pasar.",
      "tata_kelola_pengendalian_intern_status": true,
      "asesmen_kualitatif_sdm": "Rencana pengembangan SDM fokus pada keahlian analisis valas dan manajemen risiko.",
      "asesmen_kualitatif_sdm_status": true,
      "asesmen_kuantitatif_sdm": "Kecukupan SDM memadai, dengan program rekrutmen ahli valas.",
      "asesmen_kuantitatif_sdm_status": true,
      "asesmen_kepemilikan_domestik_asing": "Struktur kepemilikan tidak berubah.",
      "asesmen_kepemilikan_domestik_asing_status": true,
      "asesmen_pengendalian_domestik_asing": "Struktur pengendalian tetap kuat.",
      "asesmen_pengendalian_domestik_asing_status": true,
      "asesmen_pemenuhan_modal": "Permodalan sangat kuat, mendukung ekspansi layanan valas.",
      "asesmen_pemenuhan_modal_status": true,
      "asesmen_manajemen_risiko_it": "Manajemen risiko IT fokus pada keamanan platform trading dan data keuangan.",
      "asesmen_manajemen_risiko_it_status": true,
      "pemantauan_kepatuhan": "Pemantauan kepatuhan terhadap regulasi valas dan remitansi sangat ketat.",
      "pemantauan_kepatuhan_status": true,
      "persentase_kepemilikan_domestik": 100,
      "pengendalian_domestik": 2,
      "persentase_kepemilikan_asing": 0,
      "pengendalian_asing": 0,
      "pihak_pengendali_ubo": "Priority Group",
      "keterangan": "Laporan ini menunjukkan pertumbuhan dan keunggulan PVR di pasar valas.",
      "file_url": "https://example.com/laporan_manajemen/PVR/2024/LM-PVR-2024-001.pdf",
      "file_path": "laporan_manajemen/PVR/2024/LM-PVR-2024-001.pdf",
      "created_at": "2025-03-20T10:00:00+07:00",
      "manajemen_sign": [
        {
          "nama": "Mr. Eko Prasetyo",
          "jabatan": "Komisaris Utama",
          "klasifikasi": "Komisaris"
        },
        {
          "nama": "Ms. Fina Lestari",
          "jabatan": "Direktur Utama",
          "klasifikasi": "Direksi"
        }
      ]
    },
    {
      "sandi_pjp": "777958119",
      "nama_pjp": "PT. Artha Semesta Utama",
      "tahun_laporan": 2023,
      "nomor_surat": "LM-ASU-2023-001",
      "tanggal_surat": "2024-03-20",
      "penilaian_perkembangan_industri_sp": "Industri SP menghadapi tantangan pemulihan ekonomi.",
      "penilaian_perkembangan_industri_sp_status": true,
      "pengawasan_perkembangan_bisnis_pjp": "Bisnis ASU menunjukkan pemulihan, namun perlu strategi pertumbuhan yang jelas.",
      "pengawasan_perkembangan_bisnis_pjp_status": true,
      "pengawasan_tata_kelola_pjp": "Tata kelola dasar sudah ada, perlu peningkatan efektivitas manajemen risiko.",
      "pengawasan_tata_kelola_pjp_status": true,
      "pandangan_perbaikan_pjp": "Fokus pada efisiensi operasional dan pengembangan pasar baru.",
      "pandangan_perbaikan_pjp_status": true,
      "perubahan_komposisi_komisaris": "Tidak ada perubahan.",
      "perubahan_komposisi_komisaris_status": false,
      "implementasi_kebijakan_direksi": "Kebijakan direksi berfokus pada pemulihan dan stabilitas operasional.",
      "implementasi_kebijakan_direksi_status": true,
      "proses_pencapaian_kinerja": "Pencapaian kinerja di bawah target, namun ada tanda-tanda perbaikan.",
      "proses_pencapaian_kinerja_status": true,
      "perbandingan_target_dan_realisasi": "Target pendapatan tercapai 70%, realisasi efisiensi 65%.",
      "perbandingan_target_dan_realisasi_status": true,
      "kendala_yang_dihadapi_pjp": "Ketidakpastian ekonomi global dan dampak inflasi.",
      "kendala_yang_dihadapi_pjp_status": true,
      "tata_kelola_pengawasan_direksi_komisaris": "Pengawasan direksi dan dewan komisaris cukup, perlu lebih proaktif.",
      "tata_kelola_pengawasan_direksi_komisaris_status": true,
      "tata_kelola_risiko_sdm": "Manajemen risiko SDM perlu ditingkatkan, terutama terkait retensi karyawan.",
      "tata_kelola_risiko_sdm_status": true,
      "tata_kelola_ketersediaan_prosedur": "Prosedur dasar tersedia, perlu penyesuaian dengan kondisi pasar.",
      "tata_kelola_ketersediaan_prosedur_status": true,
      "tata_kelola_pengendalian_intern": "Sistem pengendalian intern perlu dievaluasi ulang untuk efisiensi.",
      "tata_kelola_pengendalian_intern_status": true,
      "asesmen_kualitatif_sdm": "Rencana pengembangan SDM perlu disesuaikan dengan kebutuhan pasar.",
      "asesmen_kualitatif_sdm_status": true,
      "asesmen_kuantitatif_sdm": "Kecukupan SDM memadai, namun perlu peningkatan skill.",
      "asesmen_kuantitatif_sdm_status": true,
      "asesmen_kepemilikan_domestik_asing": "Struktur kepemilikan tidak berubah.",
      "asesmen_kepemilikan_domestik_asing_status": true,
      "asesmen_pengendalian_domestik_asing": "Struktur pengendalian tetap kuat.",
      "asesmen_pengendalian_domestik_asing_status": true,
      "asesmen_pemenuhan_modal": "Permodalan cukup, namun perlu strategi untuk penguatan modal.",
      "asesmen_pemenuhan_modal_status": true,
      "asesmen_manajemen_risiko_it": "Manajemen risiko IT perlu ditingkatkan, terutama keamanan data transaksi.",
      "asesmen_manajemen_risiko_it_status": true,
      "pemantauan_kepatuhan": "Pemantauan kepatuhan dasar dilakukan, perlu lebih komprehensif.",
      "pemantauan_kepatuhan_status": true,
      "persentase_kepemilikan_domestik": 90,
      "pengendalian_domestik": 2,
      "persentase_kepemilikan_asing": 10,
      "pengendalian_asing": 0,
      "pihak_pengendali_ubo": "Artha Group",
      "keterangan": "Laporan ini mencerminkan upaya pemulihan Artha Semesta Utama.",
      "file_url": "https://example.com/laporan_manajemen/ASU/2023/LM-ASU-2023-001.pdf",
      "file_path": "laporan_manajemen/ASU/2023/LM-ASU-2023-001.pdf",
      "created_at": "2024-03-25T10:00:00+07:00",
      "manajemen_sign": [
        {
          "nama": "Mr. Guntur Wijaya",
          "jabatan": "Komisaris Utama",
          "klasifikasi": "Komisaris"
        },
        {
          "nama": "Ms. Hani Indah",
          "jabatan": "Direktur Utama",
          "klasifikasi": "Direksi"
        }
      ]
    },
    {
      "sandi_pjp": "777952522",
      "nama_pjp": "Perusahaan Umum Pegadaian",
      "tahun_laporan": 2024,
      "nomor_surat": "LM-PEG-2024-001",
      "tanggal_surat": "2025-04-01",
      "penilaian_perkembangan_industri_sp": "Industri SP gadai dan keuangan mikro stabil, potensi besar di pedesaan.",
      "penilaian_perkembangan_industri_sp_status": true,
      "pengawasan_perkembangan_bisnis_pjp": "Bisnis Pegadaian tumbuh positif, fokus pada inklusi keuangan.",
      "pengawasan_perkembangan_bisnis_pjp_status": true,
      "pengawasan_tata_kelola_pjp": "Tata kelola dan manajemen risiko sangat kuat, mendukung layanan keuangan mikro.",
      "pengawasan_tata_kelola_pjp_status": true,
      "pandangan_perbaikan_pjp": "Perluas jangkauan ke daerah pelosok dan digitalisasi layanan.",
      "pandangan_perbaikan_pjp_status": true,
      "perubahan_komposisi_komisaris": "Tidak ada perubahan.",
      "perubahan_komposisi_komisaris_status": false,
      "implementasi_kebijakan_direksi": "Kebijakan direksi berhasil mendorong inklusi keuangan dan pertumbuhan bisnis.",
      "implementasi_kebijakan_direksi_status": true,
      "proses_pencapaian_kinerja": "Pencapaian kinerja melebihi target, dengan peningkatan jumlah nasabah.",
      "proses_pencapaian_kinerja_status": true,
      "perbandingan_target_dan_realisasi": "Target nasabah tercapai 110%, realisasi pendapatan 105%.",
      "perbandingan_target_dan_realisasi_status": true,
      "kendala_yang_dihadapi_pjp": "Literasi keuangan yang masih rendah di beberapa daerah.",
      "kendala_yang_dihadapi_pjp_status": true,
      "tata_kelola_pengawasan_direksi_komisaris": "Pengawasan direksi dan dewan komisaris aktif, mendukung inovasi layanan.",
      "tata_kelola_pengawasan_direksi_komisaris_status": true,
      "tata_kelola_risiko_sdm": "Manajemen risiko SDM fokus pada pelatihan literasi keuangan dan layanan pelanggan.",
      "tata_kelola_risiko_sdm_status": true,
      "tata_kelola_ketersediaan_prosedur": "Prosedur operasional telah dioptimalkan untuk layanan mikro.",
      "tata_kelola_ketersediaan_prosedur_status": true,
      "tata_kelola_pengendalian_intern": "Sistem pengendalian intern terintegrasi dengan jaringan cabang.",
      "tata_kelola_pengendalian_intern_status": true,
      "asesmen_kualitatif_sdm": "Rencana pengembangan SDM fokus pada keahlian keuangan mikro dan digital.",
      "asesmen_kualitatif_sdm_status": true,
      "asesmen_kuantitatif_sdm": "Kecukupan SDM memadai, dengan program rekrutmen agen.",
      "asesmen_kuantitatif_sdm_status": true,
      "asesmen_kepemilikan_domestik_asing": "Struktur kepemilikan tidak berubah.",
      "asesmen_kepemilikan_domestik_asing_status": true,
      "asesmen_pengendalian_domestik_asing": "Struktur pengendalian tetap kuat.",
      "asesmen_pengendalian_domestik_asing_status": true,
      "asesmen_pemenuhan_modal": "Permodalan sangat kuat, mendukung ekspansi dan investasi.",
      "asesmen_pemenuhan_modal_status": true,
      "asesmen_manajemen_risiko_it": "Manajemen risiko IT fokus pada keamanan transaksi dan data nasabah.",
      "asesmen_manajemen_risiko_it_status": true,
      "pemantauan_kepatuhan": "Pemantauan kepatuhan terhadap regulasi keuangan mikro dan gadai.",
      "pemantauan_kepatuhan_status": true,
      "persentase_kepemilikan_domestik": 100,
      "pengendalian_domestik": 5,
      "persentase_kepemilikan_asing": 0,
      "pengendalian_asing": 0,
      "pihak_pengendali_ubo": "Pemerintah Indonesia",
      "keterangan": "Laporan ini menunjukkan peran Pegadaian dalam inklusi keuangan di Indonesia.",
      "file_url": "https://example.com/laporan_manajemen/PEG/2024/LM-PEG-2024-001.pdf",
      "file_path": "laporan_manajemen/PEG/2024/LM-PEG-2024-001.pdf",
      "created_at": "2025-04-05T10:00:00+07:00",
      "manajemen_sign": [
        {
          "nama": "Mr. Joko Susanto",
          "jabatan": "Komisaris Utama",
          "klasifikasi": "Komisaris"
        },
        {
          "nama": "Ms. Kartika Dewi",
          "jabatan": "Direktur Utama",
          "klasifikasi": "Direksi"
        }
      ]
    }
  ]
}
